pmeter/__init__.py
pmeter/app.py
pmeter/common/__init__.py
pmeter/common/action.py
pmeter/common/command.py
pmeter/common/config.py
pmeter/common/const.py
pmeter/common/decorator.py
pmeter/common/logger.py
pmeter/common/template.py
pmeter/common/utils.py
pmeter/core/__init__.py
pmeter/core/app.py
pmeter/core/jmx_test.py
pmeter/core/report.py
pmeter/core/upload.py
pmeter/etc/config.ini
pmeter-0.0.1.dist-info/METADATA
pmeter-0.0.1.dist-info/WHEEL
pmeter-0.0.1.dist-info/entry_points.txt
pmeter-0.0.1.dist-info/top_level.txt
pmeter-0.0.1.dist-info/RECORD
