Metadata-Version: 2.1
Name: pmeter
Version: 0.0.1
Summary: A Jmeter auto test tool.
Home-page: https://github.com/ddong8/pmeter
Author: donghaixing
Author-email: donghaixing8@gmail.com
License: Apache License 2.0
Requires-Dist: xlrd (==1.2.0)
Requires-Dist: pandas (==1.0.3)
Provides-Extra: testing
Requires-Dist: pytest ; extra == 'testing'
Requires-Dist: pytest-runner ; extra == 'testing'
Requires-Dist: pytest-html ; extra == 'testing'
Requires-Dist: pytest-cov ; extra == 'testing'
Requires-Dist: pytest-mock ; extra == 'testing'
